collective.soupstrainer-2.2-py3.7-nspkg.pth
collective/soupstrainer/__init__.py
collective/soupstrainer/tests.py
collective.soupstrainer-2.2.dist-info/METADATA
collective.soupstrainer-2.2.dist-info/WHEEL
collective.soupstrainer-2.2.dist-info/entry_points.txt
collective.soupstrainer-2.2.dist-info/namespace_packages.txt
collective.soupstrainer-2.2.dist-info/top_level.txt
collective.soupstrainer-2.2.dist-info/RECORD
